.long-description.html
README.rst
setup.py
src/collective/__init__.py
src/collective.folderlogo.egg-info/PKG-INFO
src/collective.folderlogo.egg-info/SOURCES.txt
src/collective.folderlogo.egg-info/dependency_links.txt
src/collective.folderlogo.egg-info/entry_points.txt
src/collective.folderlogo.egg-info/namespace_packages.txt
src/collective.folderlogo.egg-info/not-zip-safe
src/collective.folderlogo.egg-info/requires.txt
src/collective.folderlogo.egg-info/top_level.txt
src/collective/folderlogo/__init__.py
src/collective/folderlogo/configure.zcml
src/collective/folderlogo/upgrades.py
src/collective/folderlogo/upgrades.zcml
src/collective/folderlogo/Extensions/Install.py
src/collective/folderlogo/Extensions/__init__.py
src/collective/folderlogo/browser/__init__.py
src/collective/folderlogo/browser/configure.zcml
src/collective/folderlogo/browser/viewlets.py
src/collective/folderlogo/browser/templates/portal_header.pt
src/collective/folderlogo/docs/CONTRIBUTORS.rst
src/collective/folderlogo/docs/CREDITS.rst
src/collective/folderlogo/docs/HISTORY.rst
src/collective/folderlogo/docs/INSTALL.rst
src/collective/folderlogo/docs/LICENSE.rst
src/collective/folderlogo/docs/Makefile
src/collective/folderlogo/docs/README.rst
src/collective/folderlogo/docs/conf.py
src/collective/folderlogo/docs/index.rst
src/collective/folderlogo/docs/_static/.gitignore
src/collective/folderlogo/interfaces/__init__.py
src/collective/folderlogo/interfaces/layer.py
src/collective/folderlogo/profiles/default/browserlayer.xml
src/collective/folderlogo/profiles/default/metadata.xml
src/collective/folderlogo/profiles/default/registry.xml
src/collective/folderlogo/profiles/uninstall/registry.xml
src/collective/folderlogo/tests/__init__.py
src/collective/folderlogo/tests/base.py
src/collective/folderlogo/tests/test_functional.py
src/collective/folderlogo/tests/test_setup.py
src/collective/folderlogo/tests/test_upgrades.py
src/collective/folderlogo/tests/functional/browser.txt