Metadata-Version: 1.1
Name: collective.folderlogo
Version: 1.2
Summary: Easily add and change logos in different folders for Plone.
Home-page: https://github.com/collective/collective.folderlogo
Author: Taito Horiuchi
Author-email: taito.horiuchi@gmail.com
License: BSD
Platform: UNKNOWN
Classifier: Framework :: Plone
Classifier: Framework :: Plone :: 4.2
Classifier: License :: OSI Approved :: BSD License
Classifier: Programming Language :: Python
Classifier: Programming Language :: Python :: 2.7
